ic_multitool_fluxodedados/__init__.py
ic_multitool_fluxodedados/database.py
ic_multitool_fluxodedados/functions.py
ic_multitool_fluxodedados/main.py
ic_multitool_fluxodedados-0.1.0.dist-info/entry_points.txt
ic_multitool_fluxodedados-0.1.0.dist-info/WHEEL
ic_multitool_fluxodedados-0.1.0.dist-info/METADATA
ic_multitool_fluxodedados-0.1.0.dist-info/RECORD
