Metadata-Version: 2.1
Name: ic-multitool-fluxodedados
Version: 0.1.0
Summary: 
Author: Marcelo Assis
Author-email: 94455042+marceloapda@users.noreply.github.com
Requires-Python: >=3.9,<4.0
Classifier: Programming Language :: Python :: 3
Classifier: Programming Language :: Python :: 3.10
Classifier: Programming Language :: Python :: 3.9
Requires-Dist: boto3
Requires-Dist: pandas
Requires-Dist: pymysql
Requires-Dist: typer[all] (>=0.4.2,<0.5.0)
